operational_hours_local/__init__.py
operational_hours_local/operational_hours.py
operational_hours_local-0.0.28.dist-info/METADATA
operational_hours_local-0.0.28.dist-info/WHEEL
operational_hours_local-0.0.28.dist-info/top_level.txt
operational_hours_local-0.0.28.dist-info/RECORD
